driver_h/__init__.py
driver_h/driver_h.py
driver_h-0.1.6.dist-info/LICENSE.txt
driver_h-0.1.6.dist-info/METADATA
driver_h-0.1.6.dist-info/WHEEL
driver_h-0.1.6.dist-info/top_level.txt
driver_h-0.1.6.dist-info/RECORD
