Metadata-Version: 2.1
Name: driver-h
Version: 0.1.6
Summary: UNKNOWN
Home-page: https://github.com/Yaroslav1233/driver-h
Author: Yaroslav O.
Author-email: publicyaro1@gmail.com
License: UNKNOWN
Platform: UNKNOWN
Classifier: Programming Language :: Python :: 3
Classifier: License :: OSI Approved :: MIT License
Classifier: Operating System :: OS Independent
Requires-Python: >=3.6
License-File: LICENSE.txt
Requires-Dist: selenium
Requires-Dist: selenium-stealth
Requires-Dist: webdriver-manager
